silk_ml/__init__.py
silk_ml/classification.py
silk_ml/features.py
silk_ml/imbalanced.py
silk_ml/plots.py
silk_ml/scores.py
silk_ml/train.py
silk_ml-0.1.1.dist-info/LICENSE
silk_ml-0.1.1.dist-info/METADATA
silk_ml-0.1.1.dist-info/WHEEL
silk_ml-0.1.1.dist-info/top_level.txt
silk_ml-0.1.1.dist-info/RECORD
