Metadata-Version: 2.1
Name: silk-ml
Version: 0.1.1
Summary: Simple Intelligent Learning Kit (SILK) for Machine learning
Home-page: https://github.com/resuelve/silk-ml
Author: Miguel Asencio
Author-email: maasencioh@gmail.com
License: UNKNOWN
Platform: UNKNOWN
Classifier: Development Status :: 3 - Alpha
Classifier: Intended Audience :: Science/Research
Classifier: Intended Audience :: Developers
Classifier: Programming Language :: Python :: 3
Classifier: Programming Language :: Python :: 3.6
Classifier: Programming Language :: Python :: 3.7
Classifier: Topic :: Software Development
Classifier: Topic :: Scientific/Engineering
Classifier: License :: OSI Approved :: MIT License
Classifier: Operating System :: OS Independent
Requires-Python: ~=3.5
Requires-Dist: numpy
Requires-Dist: imblearn
Requires-Dist: matplotlib (==3.1.0)
Requires-Dist: pandas (==0.25.0)
Requires-Dist: scipy (==1.2.2)
Requires-Dist: seaborn (==0.9.0)
Requires-Dist: sklearn
Provides-Extra: dev
Requires-Dist: setuptools ; extra == 'dev'
Requires-Dist: wheel ; extra == 'dev'
Requires-Dist: twine ; extra == 'dev'
Requires-Dist: Sphinx ; extra == 'dev'
